nosemultiversion.py
setup.py
NoseMultiVersion.egg-info/PKG-INFO
NoseMultiVersion.egg-info/SOURCES.txt
NoseMultiVersion.egg-info/dependency_links.txt
NoseMultiVersion.egg-info/entry_points.txt
NoseMultiVersion.egg-info/requires.txt
NoseMultiVersion.egg-info/top_level.txt