Metadata-Version: 1.0
Name: NoseMultiVersion
Version: 0.1
Summary: A Nose plugin to run tests simultaneously in different versions of Python.
Home-page: UNKNOWN
Author: Kumar McMillan
Author-email: kumar.mcmillan@gmail.com
License: MIT License
Platform: UNKNOWN
